
{
  "version": 2.0,
  "questions": [
    {
          "question": "1. What are myoelectric signals?",
      "answers": {
        "a": "Electrical signals generated by the brain during motor activity",
        "b": "Electrical signals produced by muscles during contraction",
        "c": "Electrical signals produced by heart during blood pumping",
        "d": "TMechanical vibrations produced by motor movement"
      },
 
      "correctAnswer": "b",
      "difficulty": "beginner"
    },   


    {
      "question": "2. The fundamental structure in EMG is",
      "answers": {
        "a": "Bones",
        "b": "Muscles",
        "c": "Motor unit",
        "d": "Neurons"
      },
      
      "correctAnswer": "c",
      "difficulty": "beginner"
    },

    {
      "question": "3. MUAPs refer to",
      "answers": {
        "a": "Motor Unit Action Potentials",
        "b": "Muscle Unit Activation Process",
        "c": "Motor Utilization Action Potentials",
        "d": "Motor Unit Activation Process"
      },
      
      "correctAnswer": "a",
      "difficulty": "beginner"
    },

    {
      "question": "4. Placement of Surface electrodes in EMG",
      "answers": {
        "a": "Inside the selected muscle",
        "b": "Inside the skin",
        "c": "Inside the neurons",
        "d": "On the skin above the selected muscle"
      },
      
      "correctAnswer": "d",
      "difficulty": "beginner"
    },


    {
      "question": "5. EMG signals primarily reflect",
      "answers": {
        "a": "Bone movement",
        "b": "Motor unit activity",
        "c": "Heart Variability",
        "d": "Neural activity"
      },
     
      "correctAnswer": "b",
      "difficulty": "beginner"
    }
  ]
}	 